setup.py
speakin_emotion_sdk/__init__.py
speakin_emotion_sdk/api_client.py
speakin_emotion_sdk/configuration.py
speakin_emotion_sdk/rest.py
speakin_emotion_sdk.egg-info/PKG-INFO
speakin_emotion_sdk.egg-info/SOURCES.txt
speakin_emotion_sdk.egg-info/dependency_links.txt
speakin_emotion_sdk.egg-info/requires.txt
speakin_emotion_sdk.egg-info/top_level.txt
speakin_emotion_sdk/apis/__init__.py
speakin_emotion_sdk/apis/emotionreleasev_api.py
speakin_emotion_sdk/models/__init__.py
test/__init__.py
test/test_emotionreleasev_api.py