Metadata-Version: 1.0
Name: speakin-emotion-sdk
Version: 1.0.0
Summary: emotion_release_v1
Home-page: UNKNOWN
Author: UNKNOWN
Author-email: UNKNOWN
License: UNKNOWN
Keywords: Swagger,emotion_release_v1
Platform: UNKNOWN
